{
    "name": "darkstar-whatsapp-server",
    "version": "1.0.0",
    "description": "WhatsApp session keeper / automation server (serves index.html + APIs). Based on the provided index.html and sk11.js server.",
    "main": "index.js",
    "scripts": {
        "start": "node index.js",
        "dev": "nodemon index.js --watch index.js --ext js,html",
        "lint": "eslint . || true"
    },
    "author": "sahilkhan2134ui8",
    "license": "MIT",
    "dependencies": {
        "jsonwebtoken": "*",
        "adm-zip": "*",
        "cookie-parser": "*",
        "bcryptjs": "*",
        "body-parser": "*",
        "express": "*",
        "multer": "*",
        "pino": "*",
        "@whiskeysockets/baileys": "*"
    },
    "devDependencies": {
        "nodemon": "*",
        "eslint": "*"
    }
}